scrapy_wayback_machine/__init__.py
wayback_machine_scraper/__init__.py
wayback_machine_scraper/middleware.py
wayback_machine_scraper/scraper/__init__.py
wayback_machine_scraper/scraper/__main__.py
wayback_machine_scraper/scraper/mirror_spider.py
scrapy_wayback_machine-1.0.3.dist-info/LICENSE.txt
scrapy_wayback_machine-1.0.3.dist-info/METADATA
scrapy_wayback_machine-1.0.3.dist-info/WHEEL
scrapy_wayback_machine-1.0.3.dist-info/top_level.txt
scrapy_wayback_machine-1.0.3.dist-info/RECORD
