Metadata-Version: 2.1
Name: scrapy-wayback-machine
Version: 1.0.3
Summary: A Scrapy middleware for scraping Wayback Machine snapshots from archive.org.
Home-page: https://github.com/sangaline/scrapy-wayback-machine
Author: Evan Sangaline
Author-email: evan@intoli.com
License: ISC
Keywords: archive.org scrapy scraper waybackmachine middleware
Platform: UNKNOWN
Classifier: Development Status :: 5 - Production/Stable
Classifier: Framework :: Scrapy
Classifier: Topic :: Utilities
Classifier: License :: OSI Approved :: ISC License (ISCL)
Requires-Dist: cryptography
Requires-Dist: scrapy
Requires-Dist: twisted
